texcliques/__init__.py
texcliques/__main__.py
texcliques/color.py
texcliques/constants.py
texcliques/main.py
texcliques/commands/__init__.py
texcliques/commands/extract_citations.py
TeXCLIques-0.0.5.dist-info/LICENSE
TeXCLIques-0.0.5.dist-info/METADATA
TeXCLIques-0.0.5.dist-info/WHEEL
TeXCLIques-0.0.5.dist-info/entry_points.txt
TeXCLIques-0.0.5.dist-info/top_level.txt
TeXCLIques-0.0.5.dist-info/RECORD
