Metadata-Version: 2.1
Name: TeXCLIques
Version: 0.0.5
Summary: A Python CLI with utilities for scientific LaTeX documents.
Home-page: https://github.com/dimboump/texcliques
Author: Dimitris Boumparis
Author-email: dimitris@dimboump.dev
Classifier: Programming Language :: Python :: 3
Classifier: Programming Language :: Python :: 3 :: Only
Classifier: Programming Language :: Python :: Implementation :: CPython
Requires-Python: >=3.9
License-File: LICENSE
Requires-Dist: bibtexparser ==1.4.1
